github_project_automation/__init__.py
github_project_automation/cli/__init__.py
github_project_automation/cli/main.py
github_project_automation/common/__init__.py
github_project_automation/common/constants.py
github_project_automation/common/utils.py
github_project_automation/core/__init__.py
github_project_automation/core/project/__init__.py
github_project_automation/core/project/project.py
github_project_automation/core/project_item/__init__.py
github_project_automation/core/project_item/base_project_item.py
github_project_automation/core/project_item/issue.py
github_project_automation/core/project_item/pull_request.py
github_project_automation/management/__init__.py
github_project_automation/management/configuration.py
github_project_automation/management/event_manager.py
github_project_automation/management/github_client.py
github_project_automation/management/project_manager.py
github_project_automation-1.1.0.dist-info/LICENSE
github_project_automation-1.1.0.dist-info/METADATA
github_project_automation-1.1.0.dist-info/WHEEL
github_project_automation-1.1.0.dist-info/entry_points.txt
github_project_automation-1.1.0.dist-info/top_level.txt
github_project_automation-1.1.0.dist-info/RECORD
