Metadata-Version: 2.1
Name: github-project-automation
Version: 1.1.0
Summary: GitHub automatic project manager tool
Home-page: https://github.com/khulansot/github-project-automation
Author: KhulnaSoft Ltd
Author-email: info@khulnasoft.com
License: MIT
Keywords: GitHub,Project,Manager,github-project-automation,project,manage,manager
Classifier: Natural Language :: English
Classifier: License :: OSI Approved :: MIT License
Classifier: Intended Audience :: Developers
Classifier: Intended Audience :: System Administrators
Classifier: Programming Language :: Python :: 3.7
Classifier: Programming Language :: Python :: 3.8
Requires-Python: >=3.7
License-File: LICENSE
Requires-Dist: click
Requires-Dist: requests
Requires-Dist: python-dateutil
Requires-Dist: gql ==3.0.0a5
